[{"image": "http://www3.pictures.zimbio.com/gi/John+Legend+Samsung+Hope+Children+Gala+6Xpk7BeOAOcl.jpg", "data": {"genre": "rnb", "count": 9, "song": ["Ordinary People", "Good Morning", "All Of Me", "Ordinary People - Live from Spotify Milan"], "places": [["Reading, United Kingdom", [51.45351808, -0.98857337]], ["Manila, Metro Manila, Philippines", [14.44413688, 121.00397741]], ["Mount Auburn, Illinois, United States", [39.739318, -89.266507]], ["Reading, United Kingdom", [51.56562059, -3.27454495]], ["Leicester, United Kingdom", [52.63302248, -1.13127148]], ["Leighton Buzzard, United Kingdom", [51.90227525, -0.65138507]], ["Apalit, Central Luzon, Philippines", [14.95775, 120.75987]], ["Potsdam, Brandenburg, Germany", [52.381905, 13.1199934]], ["Charlotte, North Carolina, United States", [35.051045, -80.843527]]], "artist": "John Legend"}},
{"image": "http://2.bp.blogspot.com/_-AKhLCzB8_I/TAe6q7aZDFI/AAAAAAAAHNw/wDGX-pVawR8/s1600/Gloria-Gaynor.jpg", "data": {"genre": "rnb", "count": 3, "song": ["Never Can Say Goodbye", "I Will Survive"], "places": [["Leicester, United Kingdom", [52.63302248, -1.13127148]], ["Leighton Buzzard, United Kingdom", [51.90227525, -0.65138507]], ["Reading, United Kingdom", [51.45351808, -0.98857337]]], "artist": "Gloria Gaynor"}},
{"image": "http://www.magmire.net/wp-content/uploads/2012/09/Jamelia.jpg", "data": {"genre": "rnb", "count": 3, "song": ["See It In A Boy's Eyes", "DJ", "Stop"], "places": [["Reading, England, United Kingdom", [51.42949311, -0.94582087]], ["Canterbury, United Kingdom", [51.27714936, 1.07852936]], ["Southwick, England, United Kingdom", [50.83362595, -0.23791958]]], "artist": "Jamelia"}},
{"image": "http://www.rex-fox.com/wallpaper/ashanti/ashanti-37113.jpg", "data": {"genre": "rnb", "count": 3, "song": ["Breakup 2 Makeup", "Still On It - Album Version (Edited) - Collectables By Ashanti"], "places": [["Reading, United Kingdom", [51.45351808, -0.98857337]], ["Atlanta, Georgia, United States", [33.90505, -84.4802975]], ["Evergreen Park, Illinois, United States", [41.73301929, -87.6987709]]], "artist": "Ashanti"}},
{"image": "http://dawsonink.com/wordpress/wp-content/uploads/2011/05/Brownstone-e1305964524127.jpg", "data": {"genre": "rnb", "count": 2, "song": ["If You Love Me"], "places": [["High Wycombe, United Kingdom", [51.58826844, -0.68399984]], ["Reading, United Kingdom", [51.45351808, -0.98857337]]], "artist": "Brownstone"}},
{"image": "http://4tothefloor.files.wordpress.com/2010/03/pointer-sisters-02.jpg", "data": {"genre": "rnb", "count": 2, "song": ["Automatic", "I'm so Excited"], "places": [["London, United Kingdom", [51.46255891, -0.13714488]], ["Balikesir, Turkey", [39.420721, 26.807174]]], "artist": "The Pointer Sisters"}},
{"image": "http://images.mstarz.com/data/images/full/15315/mary-mary.jpg?w=600", "data": {"genre": "rnb", "count": 2, "song": ["Something Big", "Shackles"], "places": [["Pittsburg, California, United States", [38.0360672, -121.8904655]], ["Leicester, United Kingdom", [52.63302248, -1.13127148]]], "artist": "Mary Mary"}},
{"image": "http://www.newhavenrecords.com/wp-content/gallery/al-green/al_green.jpg", "data": {"genre": "rnb", "count": 2, "song": ["Take Me To The River", "Tired Of Being Alone"], "places": [["Reading, United Kingdom", [51.45351808, -0.98857337]], ["Chula Vista, California, United States", [32.598921, -117.073916]]], "artist": "Al Green"}},
{"image": "http://www.aceshowbiz.com/images/wennpic/chaka-khan-2011-cnn-heroes-02.jpg", "data": {"genre": "rnb", "count": 2, "song": ["I Feel For You", "Tight Fit"], "places": [["London, United Kingdom", [51.48023622, -0.1975017]], ["Seattle, Washington, United States", [47.67740648, -122.31508213]]], "artist": "Chaka Khan"}}]